README.md
setup.py
cheesefactory_gpg/__init__.py
cheesefactory_gpg.egg-info/PKG-INFO
cheesefactory_gpg.egg-info/SOURCES.txt
cheesefactory_gpg.egg-info/dependency_links.txt
cheesefactory_gpg.egg-info/requires.txt
cheesefactory_gpg.egg-info/top_level.txt